{
    "ぜんりょくじょしかくめい": "001",
    "いっちょくせんだいさくせん！": "002",
    "P.O.P.P.Y": "101",
    "シークレット・ドリーム": "102",
    "Stand Get Up": "103",
    "ムテキDUOエナジー": "104",
    "ヒカリノコトバ": "105",
    "We're The World": "106",
    "ネバギバラバー": "107",
    "Perfect☆STARs": "108",
    "GIRA GIRA STAR": "109",
    "きらめきのうた": "110",
    "パステルステップデイズ": "111",
    "GIRA GIRA STAR（ダークチィ）": "112",
    "ニュースタージョーカー": "113",
    "レッツ！アイプリ（ひまり）": "201",
    "レッツ！アイプリ（みつき）": "202",
    "レッツ！アイプリ（つむぎ）": "203",
    "レッツ！アイプリ（サクラ）": "204",
    "レッツ！アイプリ（タマキ）": "205",
    "レッツ！アイプリ（アイリ）": "206",
    "レッツ！アイプリ（リンリン）": "207",
    "レッツ！アイプリ（チィ）": "208",
    "レッツ！アイプリ（ひまり みつき）": "210",
    "ひまりのひみつマイソング♪": "301",
    "みつきのひみつマイソング♪": "302",
    "つむぎのひみつマイソング♪": "303",
    "サクラのひみつマイソング♪": "304",
    "タマキのひみつマイソング♪": "305",
    "アイリのひみつマイソング♪": "306",
    "リンリンのひみつマイソング♪": "307",
    "チィのひみつマイソング♪": "308",
    "ハピハピハッピー☆マイバースデー（ひまり）": "401",
    "ハピハピハッピー☆マイバースデー（みつき）": "402",
    "ハピハピハッピー☆マイバースデー（つむぎ）": "403",
    "ハピハピハッピー☆マイバースデー（サクラ）": "404",
    "ハピハピハッピー☆マイバースデー（タマキ）": "405",
    "ハピハピハッピー☆マイバースデー（アイリ）": "406",
    "ハピハピハッピー☆マイバースデー（リンリン）": "407",
    "ハピハピハッピー☆マイバースデー（チィ）": "408",
    "クリスマス・カルテット": "501",
    "オシャレまじょ♥ラブandベリーメドレー": "901"
}
