[
    {
        "title": "ドリーム",
        "groups": [
            {
                "group": "シンガー",
                "parts": ["あいらしペールピンク", "マシュマロピンク", "ぱっつんシースルー", "マスカットジュレ", "メロディペイント"]
            },
            {
                "group": "ダンサー",
                "parts": ["キャンディレモン", "はじけるダンサー", "スターデコ", "ココアクッキー", "ポップポップおだんご"]
            },
            {
                "group": "モデル",
                "parts": ["ブルーバタフライ", "クラウディナイト", "なきぼくろ", "オトナワンレン", "そよそよシャボンだま"]
            },
            {
                "group": "アーティスト",
                "parts": ["ホットラズベリー", "ビーナスステラ", "オレンジジャム", "フレンドシップハート", "くびれミディアム"]
            },
            {
                "group": "アイドル",
                "parts": ["レモンチーズケーキ", "たゆんみつあみ", "ラブきゅんスイート", "といきメロウグリーン", "ギンガムチェックリボンデコ"]
            },
            {
                "group": "インフルエンサー",
                "parts": ["ミックストイデコ", "アップルレッド", "モダンクールポニー", "かろやかナナメ", "ビーナスステラブルー"]
            },
            {
                "group": "プリンセス",
                "parts": ["フローラプリンセス", "スマートプチフラワーデコ", "ノーブルホワイト", "メイクアッププリンセス", "きらめきプリンセス"]
            },
            {
                "group": "マナマナみゃむ",
                "parts": ["みゃむライトブルー", "みゃむアイ", "みゃむだいすきメイク"]
            },
            {
                "group": "オーロラプリズムスタァ",
                "parts": ["ピュアウエディングメイク", "オーロラウエディングアイ", "プリズムストーンデコ"]
            },
            {
                "group": "プリマジスタ",
                "parts": ["まつりアイ", "まつりピンク", "コーデメイツアイ"]
            },
            {
                "group": "かしこまプリパラアイドル",
                "parts": ["らぁらアイ", "らぁらパープル", "プリパラデコ"]
            },
            {
                "group": "ボーカルドールファルル",
                "parts": ["ファルルグリーン", "ねむりのファルルアイ", "ボーカルドールアクセ"]
            },
            {
                "group": "ユメかわプリパラアイドル",
                "parts": ["ゆいスターアイ", "みちるグレー", "にのサンカクデコ"]
            },
            {
                "group": "ときのせいれいファララ",
                "parts": ["ファララクロック", "ファララティアラ", "ファララグリーン"]
            },
            {
                "group": "キラッとプリ☆チャンアイドル",
                "parts": ["みらいアイ", "えもスターデコ", "りんかブルー"]
            },
            {
                "group": "やってみたプリ☆チャンアイドル",
                "parts": ["キラッCHUメイク", "キラッとデコ", "プリ☆チャンキラッとアイ"]
            },
            {
                "group": "きせきのプリマジスタ",
                "parts": ["まつりハートデコ", "あうるメイク", "マジカルキラキラアイ"]
            },
            {
                "group": "てんちょうのプリマジスタ",
                "parts": ["ひなメイク", "あまねレッド", "パッションローズアイ"]
            },
            {
                "group": "Prizmmy☆",
                "parts": ["プリズミースターデコ", "みあスターアイ", "プリズムピンク"]
            },
            {
                "group": "いっちば〜ん！プリズムスター",
                "parts": ["シンフォニアアイ", "ほほえみのシンフォニアメイク", "シンフォニアバタフライデコ"]
            },
            {
                "group": "バーチャルシンガー",
                "parts": ["はつねミクグリーン", "はつねミクエムじバング", "はつねミクアイ", "はつねミクツインテ"]
            },
            {
                "group": "ゆきのバーチャルシンガー",
                "parts": ["ゆきみくライトブルー", "ゆきミクアイ", "ラビット・ユキネデコ"]
            },
            {
                "group": "さくらのバーチャルシンガー",
                "parts": ["さくらミクアイ", "さくらミクピンク", "さくらミクデコ"]
            },
            {
                "group": "オシャレまじょ",
                "parts": ["ラブブラウン", "ベリーブルーグリーン", "ラブブラウンアイ", "ベリーブルーアイ"]
            }
        ]
    },
    {
        "title": "ひみつタイム",
        "groups": [
            {
                "group": "アニメキャラのひみつ",
                "parts": [
                    "むげんだいリボンデコ", "ひまりハートデコ", "みつきムーンデコ", "つむぎクローバーデコ", "つむぎプリンセスデコ",
                    "チィおんぷデコ", "サクラバタフライデコ", "タマキローズデコ", "アイリキャンディデコ", "リンリンベアデコ"
                ]
            },
            {
                "group": "みんなのひみつ",
                "parts": [
                    "きらりアプリコットピーチ", "ナナメバング", "ジューシーグレープ", "マロンブラウン", "おひめさまカット",
                    "ヒスイグリーン", "ゆるやかウェーブ", "トランプメイク", "フローズンスノー", "ミルキーいちご",
                    "おしとやかめがね", "うちまきスウィート", "ゴールドスマイル", "ブラッドオレンジ", "トゲトゲサイド"
                ]
            }
        ]
    },
    {
        "title": "ひみつダイアリー",
        "groups": [
            {
                "group": "ひみつダイアリー",
                "parts": ["ひみつのわたしメイク", "ひみつのわたしカラー", "ひみつのわたしアイ", "ひみつのわたしデコ", "ひみつのわたしバング", "ひみつのわたしアイパッチ"]
            }
        ]
    },
    {
        "title": "ツアー",
        "groups": [
            {
                "group": "スプリングツアー2024",
                "parts": ["あさづみグリーン", "さくらんぼデコ", "スプリングミックス"]
            },
            {
                "group": "レイニーツアー2024",
                "parts": ["レイニードロップ", "あめあめしずく", "せのびみつあみ"]
            },
            {
                "group": "サマーツアー2024",
                "parts": ["しゅわしゅわソーダ", "クラッシュオレンジ", "マジックアワーグラス", "オンまゆシースルー"]
            },
            {
                "group": "オータムツアー2024",
                "parts": ["ハッピーハロウィン", "ウィッチパープル", "ロングカーテン", "ハロウィンデコ"]
            },
            {
                "group": "ウィンターツアー2024→2025",
                "parts": ["さむぞらウィンター", "ピュアアイボリー", "スノークリスタルデコ", "グレイシャドウ"]
            },
            {
                "group": "ひみつのミラクルツアー2025",
                "parts": ["バーチャルワールド", "むてきミラクルアイ", "ゆったりおさげ", "グレイスローズ"]
            }
        ]
    },
    {
        "title": "マイキャラフェス",
        "groups": [
            {
                "group": "3だん",
                "parts": ["マーメイドデコ", "ぱっつんエムじ"]
            },
            {
                "group": "4だん",
                "parts": ["カルスタトランプデコ", "プリンスウルフ"]
            },
            {
                "group": "5だん",
                "parts": ["ほがらかまっちゃ", "ときめきツインテール"]
            },
            {
                "group": "6だん",
                "parts": ["シャイニーゴールド", "こなれセンターパート"]
            }
        ]
    }
]
